{"qDW2WpfKZjq2kYeITWpVzg==":"norden-corcho-1-128x145.png","cGu06MWn24RwfBjIT9DopA==":"norden-corcho-2-128x145.png","KnovEaubLkC2dyieTgrxWg==":"norden-corcho-3-128x145.png","gVGSYQdi8IDU8xa8s6GP8w==":"norden-corcho-4-128x145.png","ewwg9tY+5nrweYZgqKTm5w==":"img_20170430-114416733-2000x1500.jpg","BUEKb/1LoJqEm1MNbSpl6g==":"img_20200512-92819-916x687.jpg","1aAas6pHAs4Fr8eqTGLulA==":"img_20190725-141031-786x590.jpg","e6RE0fI3lDRYim424epZFw==":"img-3279-786x1048.jpg","4RlKXQ+HpZE+XsG7RyjlUg==":"img_20200512-92820-916x687.jpg","faaA3bKqqRHVWLjCF8uuvw==":"img_20200512-92820-916x687.jpeg","fhDCPovGILZAbvvX9wyPog==":"img_20200512-92821-916x687.jpeg","S11EM8r/IosfknoieLhgRg==":"img_20200512-92822-916x687.jpeg","lz4WCulFoQTRjrfaA5PGgQ==":"img_20200512-92823-916x687.jpeg","OnvItm1U8S8aciol/pxpXQ==":"img_20200512-92819-916x687.jpeg","6KAMPYDVkSCN6xiE/G/jeQ==":"2-1332x1080.jpeg","YVGS9XX26OyTMktNqUeWPw==":"20190812_234328-animation.png","eSqcm2RL6hcp0zu/NC8S5w==":"20190812_234328-animation.gif","H4XAzleyxmDU8HaafUmOSw==":"img-3279-786x1048.jpeg","2GDwAF27dXYwnxbdubdggw==":"img-3280-786x1048.jpeg","SLxFlpYYJl1Kfe3glpZ0AA==":"img-3281-786x1048.jpeg","OPfNx20qiw4O0iFZ9UFTPQ==":"2-676x548.jpeg","Sk37AYy/GFwhmp1Gba2RuQ==":"img_20200512-92824-916x687.jpeg","jIfAEcU8Ku8raRy4bUC8aQ==":"img_20200512-92825-916x687.jpeg","vbswRJubeFBkCq3uflKFiQ==":"img_20200512-92826-916x687.jpeg","16JL+zptR9Zzh/Pr9FmTKw==":"img_20200512-92827-916x687.jpeg","4kSqySINmTSaYvcYu28Atw==":"img_20200512-92828-916x687.jpeg","e5xZ21rcT1SdmH23EuSliA==":"norden_corcho-192x218.png","RtH3uGisztZ9WRpHWehLAQ==":"norden_corcho-1-192x218.png","VKbPF2QsHwxbAPGkbg9NtA==":"img-3282-786x1048.jpeg","j0kkzP/1alOjHWZbL9uM2Q==":"img_20190725-141031-786x590.jpeg","etrzCrhdNT4I018FXYYIhA==":"img_20190725-141032-786x590.jpeg","SOxY6vSx0crjshjODzIPxQ==":"mbr-534x358.jpg","upouKNMLNikyItk9sQGwaA==":"bajar3-1076x1435.jpeg","IslhUj6jcYmxwcnIXiHfbw==":"bajar3-1-1076x1435.jpeg","l2NxVt/gICHdtMgxuVP6RQ==":"cristina1-515x687.jpeg","00zZUyXhpQoaC0uKo25qvA==":"product1.jpg","mIIbxW0r7dEZSbMPwcoYdg==":"background2.jpg","UAc7kepzJPkrSn4uqTRvmw==":"background4.jpg","8pQpSjM/9+900lQzLEUq5A==":"mantaxxl-salka-696x928.jpg","nqMPpC1BXil0o9YPx4fV4g==":"mantaxxx-boden-696x928.jpg","LzF+VZpBFhIeA9wIdgRs3w==":"mantaxxl-luba-696x927.jpg","cciGStOZYPlyURcoSfkFFw==":"mantaxxl-lind-696x928.jpg","+h261hdYuelr3iZAKF8vyg==":"mantaxxl-ellia-696x928.jpg","zT+Mv1vz2qa5bK/TlMqoOg==":"mantaxxl-norden-696x809.jpg","rym1vciK+sp9YCVP11s9rA==":"20200713_160415-1-696x809.jpg","+37PkX/aTwI5PCfXPh1scw==":"mantaxxl-norden-696x809.jpeg","JgsmTmzm1+mpNoYCVgpR7w==":"mantaxxl-norden-1-696x809.jpeg","zXrnl8cY1MhY/ybW46aLWA==":"mantaxxl-norden-2-696x809.jpeg","BJwKtZke4gvzjbawZiF43A==":"mantaxxl-norden-3-696x809.jpeg","imb2rvqhiWBF5GSt4Z5hiQ==":"mantaxxl-norden-4-696x809.jpeg","sdsIkhf5E31DuYP2NobOxA==":"mantaxxl-norden-696x928.jpg","ccM5kL5Cl56qBSCUiqEFJw==":"mantaxxl-ellia-1-696x928.jpg","h8aUKYlwCwExRGeEuYgz8g==":"mantaxxl-riva-696x928.jpg","SF4MYfMdIdspEx0ah4gssw==":"mantaxxl-ris-696x928.jpg","94cvtE9steHD1BqT6yJ7zg==":"mantaxxl-boden-696x928.jpg","G3knsyZqfJMz3sYerMYvjg==":"mantaxxl-andina-696x928.jpg","rOtKcelLNV1qCpObV4PKlA==":"mantaxxl-ana-696x522.jpg","coq52v34JPO+DVOIGpb0iw==":"mantaxxl-blume-696x928.jpg","4JBluPTXLAhFhoIqQT61qA==":"mantaxxl-ana2-696x928.jpg","G+8lQDbMxpMbwSss6thj7Q==":"mantaxxl-brenu-696x928.jpg","DLDKT4xntMJq49+X0jy5NQ==":"mantaxxl-lind-750x1000.jpg","x4LErK7J5UtsQ+VClaWjCg==":"mantaxxl-lind-galery-960x1280.jpg","T3esNdLUu9e3p28jsLIigg==":"mantaxxl-lind-galery2-960x1280.jpg","xTqRqyrrHHJxADCVtb3uiA==":"mantaxxl-lind-galery3-960x1280.jpg"}